mmmint/__init__.py
mmmint/registration_recognition/__init__.py
mmmint/registration_recognition/__main__.py
mmmint/registration_recognition/sdk.py
mmmint/registration_recognition/test_sdk.py
mmmint_registration_recognition-2.1.1.dist-info/METADATA
mmmint_registration_recognition-2.1.1.dist-info/WHEEL
mmmint_registration_recognition-2.1.1.dist-info/top_level.txt
mmmint_registration_recognition-2.1.1.dist-info/RECORD
