Metadata-Version: 2.1
Name: mmmint-registration-recognition
Version: 2.1.1
Summary: An interface to execute Fahrzeugschein API commands using Python
Home-page: https://api.mmmint.ai/fahrzeugschein/v1/docs
Author: MMM Intelligence UG
Author-email: info@mmmint.ai.com
License: UNKNOWN
Platform: UNKNOWN
Classifier: Development Status :: 4 - Beta
Classifier: Intended Audience :: Developers
Classifier: Intended Audience :: System Administrators
Classifier: Programming Language :: Python
Classifier: Programming Language :: Python :: 3
Classifier: Programming Language :: Python :: 3.7
Classifier: Programming Language :: Python :: 3.8
Requires-Python: >=3.7
Requires-Dist: requests
Requires-Dist: click
